{"title": "Bread Baking Basics", "history": [{"speaker": "You", "content": "how do i make bread?", "isExpanded": false}, {"speaker": "Assistant", "content": "Making bread from scratch can be a rewarding experience. Here's a basic recipe to get you started:\n\n### Basic Bread Recipe\n\n#### Ingredients:\n- **3 \u00be cups (450g) all-purpose flour**: You can also use bread flour for a slightly different texture.\n- **1 \u00bd teaspoons salt**\n- **1 \u00bc teaspoons active dry yeast or instant yeast**\n- **1 \u00bd cups (360ml) warm water**: Ideally around 110\u00b0F (43\u00b0C). Not too hot, or it will kill the yeast.\n\n#### Optional Ingredients:\n- **1-2 tablespoons sugar or honey**: Helps feed the yeast and can add sweetness.\n- **2 tablespoons olive oil or melted butter**: Adds richness and moisture to the bread.\n\n#### Instructions:\n\n1. **Activate the Yeast** (if using active dry yeast):\n   - In a small bowl, combine the warm water and sugar or honey if using.\n   - Sprinkle the yeast on top. Let it sit for about 5-10 minutes until it becomes frothy. This step ensures the yeast is active. (Skip this step if using instant yeast and mix it directly with the flour).\n\n2. **Mix the Dough**:\n   - In a large mixing bowl, combine the flour and salt.\n   - Add the yeast mixture (or water if using instant yeast), and any optional oil or butter.\n   - Stir until a dough begins to form.\n\n3. **Knead the Dough**:\n   - Transfer the dough to a floured surface and knead it for about 8-10 minutes. The dough should be smooth and elastic. If it's too sticky, add a little more flour, a tablespoon at a time. If it's too dry, add a small amount of water.\n\n4. **First Rise**:\n   - Place the dough in a lightly oiled bowl, turning it to coat all sides.\n   - Cover the bowl with a damp cloth or plastic wrap.\n   - Let it rise in a warm place for about 1-2 hours, or until it has doubled in size.\n\n5. **Shape the Dough**:\n   - Punch down the risen dough to release air.\n   - Transfer it back to the floured surface and shape it into a loaf or divide it into rolls.\n   - Place the shaped dough into a greased loaf pan or onto a baking sheet.\n\n6. **Second Rise**:\n   - Cover and let it rise again for about 30-60 minutes, until it has roughly doubled in size.\n\n7. **Preheat the Oven**:\n   - Preheat your oven to 375\u00b0F (190\u00b0C).\n\n8. **Bake**:\n   - Bake the bread for 25-35 minutes, or until it sounds hollow when tapped on the bottom and is golden brown.\n   - If you're unsure, an internal temperature of around 190-200\u00b0F (88-93\u00b0C) indicates the bread is done.\n\n9. **Cool**:\n   - Remove the bread from the oven and let it cool on a wire rack before slicing.\n\n### Tips:\n- **For a crustier bread**, you can place a shallow pan of water on the bottom rack of the oven while baking.\n- **Experiment with adding seeds, herbs, or cheese** to the dough for different flavors.\n- **Allowing the bread to cool completely before slicing** will improve texture and prevent it from being doughy inside.\n\nEnjoy your homemade bread!"}, {"speaker": "You", "content": "how do i make scones", "isExpanded": false}, {"speaker": "Assistant", "content": "Making scones is a simple and rewarding process. Here\u2019s a basic recipe to get you started:\n\n### Ingredients:\n- 2 cups (250g) all-purpose flour\n- 1/4 cup (50g) granulated sugar\n- 1 tablespoon baking powder\n- 1/2 teaspoon salt\n- 1/2 cup (115g) cold unsalted butter, cut into small cubes\n- 1/2 cup (120ml) heavy cream or buttermilk (plus extra for brushing)\n- 1 large egg\n- 1 teaspoon vanilla extract\n\n### Optional Add-ins:\n- 1/2 cup (75g) dried fruit (e.g., raisins, currants, or cranberries)\n- Zest of 1 lemon or orange\n- 1/2 cup (75g) chocolate chips or chunks\n\n### Instructions:\n\n1. **Preheat Oven**: Preheat your oven to 400\u00b0F (200\u00b0C) and line a baking sheet with parchment paper.\n\n2. **Mix Dry Ingredients**: In a large bowl, whisk together the flour, sugar, baking powder, and salt.\n\n3. **Cut in Butter**: Add the cold butter cubes to the dry ingredients. Use a pastry cutter, two knives, or your fingertips to cut the butter into the flour mixture until it resembles coarse crumbs.\n\n4. **Add Liquid Ingredients**: In a separate bowl, whisk together the heavy cream (or buttermilk), egg, and vanilla extract. Pour the wet ingredients into the dry mixture and stir until just combined. Do not overmix.\n\n5. **Add Optional Ingredients**: If you\u2019re using any add-ins (dried fruit, zest, chocolate chips), gently fold them into the dough now.\n\n6. **Shape Dough**: Turn the dough out onto a lightly floured surface. Gently gather and press it into a round disk about 1 inch (2.5 cm) thick.\n\n7. **Cut Scones**: Using a sharp knife, cut the disk into 8 wedges (like a pizza), or use a round biscuit cutter for a more traditional scone shape.\n\n8. **Prepare for Baking**: Transfer the scones to the prepared baking sheet. Brush the tops lightly with extra cream or buttermilk to help them brown.\n\n9. **Bake**: Bake in the preheated oven for about 15-20 minutes, or until the scones are golden brown and a toothpick inserted into the center comes out clean.\n\n10. **Cool and Serve**: Allow the scones to cool on a wire rack for a few minutes before serving. Enjoy them warm with butter, clotted cream, and jam.\n\n### Tips:\n- For flakier scones, ensure your butter is very cold. You can even chill it in the freezer for a few minutes before cutting it into the flour.\n- Don't overwork the dough; handle it as little as possible to keep the scones tender.\n- Customize your scones with your favorite flavors and add-ins.\n\nEnjoy your freshly baked scones!"}]}